lambdipy/__init__.py
lambdipy/cli.py
lambdipy/package_build.py
lambdipy/project_build.py
lambdipy/release.py
lambdipy/releases/numba/0.43.1/build.python3.6-0xd.json
lambdipy/releases/numba/0.43.1/build.python3.7-0xd.json
lambdipy/releases/numpy/1.13.3/build.python2.7.json
lambdipy/releases/numpy/1.13.3/build.python3.6.json
lambdipy/releases/numpy/1.14.6/build.python2.7.json
lambdipy/releases/numpy/1.14.6/build.python3.6.json
lambdipy/releases/numpy/1.14.6/build.python3.7.json
lambdipy/releases/numpy/1.14.6/build.python3.8.json
lambdipy/releases/numpy/1.15.1/build.python2.7.json
lambdipy/releases/numpy/1.15.1/build.python3.6.json
lambdipy/releases/numpy/1.15.1/build.python3.7.json
lambdipy/releases/numpy/1.15.1/build.python3.8.json
lambdipy/releases/numpy/1.15.2/build.python2.7.json
lambdipy/releases/numpy/1.15.2/build.python3.6.json
lambdipy/releases/numpy/1.15.2/build.python3.7.json
lambdipy/releases/numpy/1.15.2/build.python3.8.json
lambdipy/releases/numpy/1.15.3/build.python2.7.json
lambdipy/releases/numpy/1.15.3/build.python3.6.json
lambdipy/releases/numpy/1.15.3/build.python3.7.json
lambdipy/releases/numpy/1.15.3/build.python3.8.json
lambdipy/releases/numpy/1.15.4/build.python2.7.json
lambdipy/releases/numpy/1.15.4/build.python3.6.json
lambdipy/releases/numpy/1.15.4/build.python3.7.json
lambdipy/releases/numpy/1.15.4/build.python3.8.json
lambdipy/releases/numpy/1.16.0/build.python2.7.json
lambdipy/releases/numpy/1.16.0/build.python3.6.json
lambdipy/releases/numpy/1.16.0/build.python3.7.json
lambdipy/releases/numpy/1.16.0/build.python3.8.json
lambdipy/releases/numpy/1.16.1/build.python2.7.json
lambdipy/releases/numpy/1.16.1/build.python3.6.json
lambdipy/releases/numpy/1.16.1/build.python3.7.json
lambdipy/releases/numpy/1.16.1/build.python3.8.json
lambdipy/releases/numpy/1.16.2/build.python2.7.json
lambdipy/releases/numpy/1.16.2/build.python3.6.json
lambdipy/releases/numpy/1.16.2/build.python3.7.json
lambdipy/releases/numpy/1.16.2/build.python3.8.json
lambdipy-0.1.7.dist-info/LICENSE
lambdipy-0.1.7.dist-info/METADATA
lambdipy-0.1.7.dist-info/WHEEL
lambdipy-0.1.7.dist-info/entry_points.txt
lambdipy-0.1.7.dist-info/top_level.txt
lambdipy-0.1.7.dist-info/RECORD
