Metadata-Version: 2.1
Name: lambdipy
Version: 0.1.7
Summary: A tool for building and packaging python packages for AWS Lambda.
Home-page: https://github.com/customink/lambdipy
Author: Andrej Hoos
Author-email: andrej.hoos@gmail.com
License: BSD
Platform: any
Classifier: Development Status :: 2 - Pre-Alpha
Classifier: Environment :: Console
Classifier: Intended Audience :: Developers
Classifier: License :: OSI Approved :: BSD License
Classifier: Operating System :: POSIX
Classifier: Operating System :: MacOS
Classifier: Operating System :: Unix
Classifier: Operating System :: Microsoft :: Windows
Classifier: Programming Language :: Python
Classifier: Programming Language :: Python :: 2
Classifier: Programming Language :: Python :: 3
Classifier: Topic :: Software Development :: Libraries :: Python Modules
Requires-Dist: click
Requires-Dist: pygithub
Requires-Dist: docker
Requires-Dist: requirementslib
Requires-Dist: pipenv
Requires-Dist: tqdm
